[{"symbol":"ENAUSDT","fundingTime":1730419200000,"fundingRate":"-0.00051655","markPrice":"0.36240000"},{"symbol":"ENAUSDT","fundingTime":1730433600000,"fundingRate":"-0.00075016","markPrice":"0.36340000"},{"symbol":"ENAUSDT","fundingTime":1730448000000,"fundingRate":"-0.00049765","markPrice":"0.35082108"},{"symbol":"ENAUSDT","fundingTime":1730462400000,"fundingRate":"-0.00021074","markPrice":"0.36927661"},{"symbol":"ENAUSDT","fundingTime":1730476800000,"fundingRate":"-0.00011027","markPrice":"0.36940000"},{"symbol":"ENAUSDT","fundingTime":1730491200001,"fundingRate":"-0.00028447","markPrice":"0.36946282"},{"symbol":"ENAUSDT","fundingTime":1730505600000,"fundingRate":"-0.00056879","markPrice":"0.36865014"}]