[{"symbol":"ENAUSDT","fundingTime":1715385600000,"fundingRate":"0.00005000","markPrice":"0.84700000"},{"symbol":"ENAUSDT","fundingTime":1715400000000,"fundingRate":"-0.00009523","markPrice":"0.85710000"},{"symbol":"ENAUSDT","fundingTime":1715414400000,"fundingRate":"-0.00003420","markPrice":"0.85949122"},{"symbol":"ENAUSDT","fundingTime":1715428800000,"fundingRate":"0.00005000","markPrice":"0.84230000"},{"symbol":"ENAUSDT","fundingTime":1715443200000,"fundingRate":"0.00005000","markPrice":"0.86554224"},{"symbol":"ENAUSDT","fundingTime":1715457600000,"fundingRate":"0.00005000","markPrice":"0.85423145"},{"symbol":"ENAUSDT","fundingTime":1715472000000,"fundingRate":"0.00003878","markPrice":"0.84080000"}]