[{"symbol":"ENAUSDT","fundingTime":1736985600000,"fundingRate":"-0.00007203","markPrice":"0.94308746"},{"symbol":"ENAUSDT","fundingTime":1737000000000,"fundingRate":"0.00003171","markPrice":"0.90797223"},{"symbol":"ENAUSDT","fundingTime":1737014400000,"fundingRate":"-0.00028672","markPrice":"0.90810757"},{"symbol":"ENAUSDT","fundingTime":1737028800000,"fundingRate":"-0.00021895","markPrice":"0.90610000"},{"symbol":"ENAUSDT","fundingTime":1737043200000,"fundingRate":"-0.00041039","markPrice":"0.91016919"},{"symbol":"ENAUSDT","fundingTime":1737057600000,"fundingRate":"-0.00011269","markPrice":"0.92410811"}]